incrementalconvexhull/__init__.py
incrementalconvexhull/__main__.py
incrementalconvexhull/graph.py
incrementalconvexhull/main.py
incrementalconvexhull/point.py
incrementalconvexhull/test_graph.py
incremental_convex_hull-1.0.1.dist-info/LICENSE
incremental_convex_hull-1.0.1.dist-info/METADATA
incremental_convex_hull-1.0.1.dist-info/WHEEL
incremental_convex_hull-1.0.1.dist-info/entry_points.txt
incremental_convex_hull-1.0.1.dist-info/top_level.txt
incremental_convex_hull-1.0.1.dist-info/RECORD
