Metadata-Version: 2.1
Name: incremental-convex-hull
Version: 1.0.1
Summary: Incremental convex hull builder and visualizer
Home-page: https://github.com/HactarCE/IncrementalConvexHull
Author: HactarCE, Manali Shirsekar, Neill Robson
License: GPLv3
Platform: UNKNOWN
Classifier: License :: OSI Approved :: GNU General Public License v3 or later (GPLv3+)
Classifier: Programming Language :: Python :: 3
Classifier: Programming Language :: Python :: 3.9
Requires-Dist: numpy
Requires-Dist: pyglet
